d_latch.v
module d_latch(
    input enb,rst,d,
    output reg q,q_bar

);

always @ (enb)begin
    if(!enb)begin
        //reset logic
        if(rst) begin
            q = 1'b0;
            q_bar = 1'b1;
        end

        else begin
            q <= d;
            q_bar <= ~d;
        end
    end
end
endmodule

`timescale 1ps/1ps
module tb;

reg enb,rst,d;
wire q,q_bar;

d_latch uut(enb,rst,d,q,q_bar);
initial begin
    {enb,rst,d} = 0;
end

always #5 enb = ~enb ;

initial begin
    $dumpfile("d_latch.vcd");
    $dumpvars(0,tb);
    rst = 1;
    #10;
    rst = 0;
    d = 1;
    #10;
    d =0;
    #10;
    rst = 1;
    #5;
    
    $finish ;
end
endmodule

d_latch.vcd
$date
	Thu Aug 13 20:22:06 2026
$end
$version
	Icarus Verilog
$end
$timescale
	1ps
$end
$scope module tb $end
$var wire 1 ! q_bar $end
$var wire 1 " q $end
$var reg 1 # d $end
$var reg 1 $ enb $end
$var reg 1 % rst $end
$scope module uut $end
$var wire 1 # d $end
$var wire 1 $ enb $end
$var wire 1 % rst $end
$var reg 1 " q $end
$var reg 1 ! q_bar $end
$upscope $end
$upscope $end
$enddefinitions $end
$comment Show the parameter values. $end
$dumpall
$end
#0
$dumpvars
1%
0$
0#
0"
1!
$end
#5
1$
#10
0!
1"
0$
1#
0%
#15
1$
#20
1!
0"
0$
0#
#25
1$
#30
0$
1%
#35
1$
