jk_latch.v
module jk_latch(
    input enb,rst,j,k,
    output reg q,q_bar
);

always @(enb)begin
    if(enb)begin
        //reset logic 
        if(rst)begin
            q <= 0;
            q_bar <= 0;
         end

         //set 
         else if(j == 0 && k == 0)begin
            q <= q;
            q_bar <= q_bar;
         end

         else if(j == 0 && k == 1)begin
            q <= 0;
            q_bar <=1;
         end

         else if(j == 1 && k == 0)begin
            q <= 1;
            q_bar <= 0;
         end

         else if(j ==1 && k == 1)begin
            q <= ~q;
            q_bar <= ~q_bar;
         end
    end
end
endmodule


`timescale 1ps/1ps

module tb;

reg enb,rst,j,k;
wire q,q_bar;

jk_latch uut(enb,rst,j,k,q,q_bar);

initial begin
    {enb,rst,j,k} = 0;
end

always #5 enb = ~enb;
initial begin
    $dumpfile("jk_latch.vcd");
    $dumpvars(0,tb);
    rst = 1;
    #10;
    rst = 0;
    #10;
    //j=0;k=0; 
    #10;
    j=0;k=1; #10;
    j=1;k=0; #10;
    j=1;k=1; #10;
    rst = 1;
    #10;
    rst =0;
    $finish;
end
endmodule

jk_latch.vcd
$date
	Thu Aug 13 21:07:38 2026
$end
$version
	Icarus Verilog
$end
$timescale
	1ps
$end
$scope module tb $end
$var wire 1 ! q_bar $end
$var wire 1 " q $end
$var reg 1 # enb $end
$var reg 1 $ j $end
$var reg 1 % k $end
$var reg 1 & rst $end
$scope module uut $end
$var wire 1 # enb $end
$var wire 1 $ j $end
$var wire 1 % k $end
$var wire 1 & rst $end
$var reg 1 " q $end
$var reg 1 ! q_bar $end
$upscope $end
$upscope $end
$enddefinitions $end
$comment Show the parameter values. $end
$dumpall
$end
#0
$dumpvars
1&
0%
0$
0#
x"
x!
$end
#5
0!
0"
1#
#10
0#
0&
#15
1#
#20
0#
#25
1#
#30
0#
1%
#35
1!
1#
#40
0#
0%
1$
#45
0!
1"
1#
#50
0#
1%
#55
1!
0"
1#
#60
0#
1&
#65
0!
1#
#70
0#
0&
