pipo.v
module siso(
    input enb,clk,rst,
    input [3:0]p_in, 
    output reg [3:0]p_out
);
reg [3:0] temp;

always @(posedge clk) begin
    if (rst) begin
        p_out <= 4'b0000;
    end
    else begin
        p_out <= p_in;
    end
end

endmodule


`timescale 1ps/1ps
module tb;

reg enb,clk,rst;
reg [3:0]p_in;
wire [3:0]p_out;

siso dut(
    enb,clk,rst,p_in,p_out
);

initial begin
    {enb,clk,rst,p_in} = 0;
end

always #5 clk = ~clk;
initial begin
    $dumpfile("pipo.vcd");
    $dumpvars(0,tb);
    rst =1;
    #10;
    rst =0;
    enb = 1; 
    p_in = 1;
    #10;
    p_in= 0;
    #10;
    p_in =0 ; #10;
    p_in =1; #10;
     enb =0;
    #60;
   
    $finish;

end
endmodule

pipo.vcd
$date
	Fri Aug 14 06:37:47 2026
$end
$version
	Icarus Verilog
$end
$timescale
	1ps
$end
$scope module tb $end
$var wire 4 ! p_out [3:0] $end
$var reg 1 " clk $end
$var reg 1 # enb $end
$var reg 4 $ p_in [3:0] $end
$var reg 1 % rst $end
$scope module dut $end
$var wire 1 " clk $end
$var wire 1 # enb $end
$var wire 4 & p_in [3:0] $end
$var wire 1 % rst $end
$var reg 4 ' p_out [3:0] $end
$upscope $end
$upscope $end
$enddefinitions $end
$comment Show the parameter values. $end
$dumpall
$end
#0
$dumpvars
bx '
b0 &
1%
b0 $
0#
0"
bx !
$end
#5
b0 !
b0 '
1"
#10
0"
b1 $
b1 &
1#
0%
#15
b1 !
b1 '
1"
#20
0"
b0 $
b0 &
#25
b0 !
b0 '
1"
#30
0"
#35
1"
#40
0"
b1 $
b1 &
#45
b1 !
b1 '
1"
#50
0"
0#
