piso.v
module siso(
    input clk,rst,enb,
    input [3:0]p_in, 
    output reg s_out
);
reg [3:0] temp;

always @(posedge clk)begin
    if(rst)begin
        s_out <= 0;
        temp <= 4'b0000;
    end

    else if(enb == 1)begin
        temp <= p_in;
    end
     else if(enb ==0)begin
        s_out <= temp[0];
        temp <= temp >> 1'b1;
     end

end

endmodule


`timescale 1ps/1ps
module tb;

reg clk,rst,enb;
reg [3:0]p_in;
wire s_out;

siso dut(
    clk,rst,enb,p_in,s_out
);

initial begin
    {clk,rst,enb,p_in} = 0;
end

always #5 clk = ~clk;
initial begin
    $dumpfile("piso.vcd");
    $dumpvars(0,tb);
    rst =1;
    #10;
    rst =0;
    enb=1;
    p_in = 4'b1001;
    #10;
    enb = 0;
    #60;
    $finish;

end
endmodule

piso.vcd
$date
	Fri Aug 14 06:54:12 2026
$end
$version
	Icarus Verilog
$end
$timescale
	1ps
$end
$scope module tb $end
$var wire 1 ! s_out $end
$var reg 1 " clk $end
$var reg 1 # enb $end
$var reg 4 $ p_in [3:0] $end
$var reg 1 % rst $end
$scope module dut $end
$var wire 1 " clk $end
$var wire 1 # enb $end
$var wire 4 & p_in [3:0] $end
$var wire 1 % rst $end
$var reg 1 ! s_out $end
$var reg 4 ' temp [3:0] $end
$upscope $end
$upscope $end
$enddefinitions $end
$comment Show the parameter values. $end
$dumpall
$end
#0
$dumpvars
bx '
b0 &
1%
b0 $
0#
0"
x!
$end
#5
b0 '
0!
1"
#10
0"
b1001 $
b1001 &
1#
0%
#15
b1001 '
1"
#20
0"
0#
#25
b100 '
1!
1"
#30
0"
#35
b10 '
0!
1"
#40
0"
#45
b1 '
1"
#50
0"
#55
b0 '
1!
1"
#60
0"
#65
0!
1"
