sipo.v
module siso(
    input enb,clk,rst,s_in, 
    output reg [3:0]p_out
);
reg [3:0] temp;

always @(posedge clk) begin
    if (rst) begin
        p_out <= 4'b0000;
    end
    else begin
        p_out <= {s_in, p_out[3:1]};
    end
end

endmodule


`timescale 1ps/1ps
module tb;

reg enb,clk,rst,s_in;
wire [3:0]p_out;

siso dut(
    enb,clk,rst,s_in,p_out
);

initial begin
    {enb,clk,rst,s_in} = 0;
end

always #5 clk = ~clk;
initial begin
    $dumpfile("sipo.vcd");
    $dumpvars(0,tb);
    rst =1;
    #10;
    rst =0;
    enb = 1; 
    s_in = 1;
    #10;
    s_in= 0;
    #10;
    s_in =0 ; #10;
    s_in =1; #10;
     enb =0;
    #60;
   
    $finish;

end
endmodule

sipo.vcd
$date
	Fri Aug 14 06:37:25 2026
$end
$version
	Icarus Verilog
$end
$timescale
	1ps
$end
$scope module tb $end
$var wire 4 ! p_out [3:0] $end
$var reg 1 " clk $end
$var reg 1 # enb $end
$var reg 1 $ rst $end
$var reg 1 % s_in $end
$scope module dut $end
$var wire 1 " clk $end
$var wire 1 # enb $end
$var wire 1 $ rst $end
$var wire 1 % s_in $end
$var reg 4 & p_out [3:0] $end
$upscope $end
$upscope $end
$enddefinitions $end
$comment Show the parameter values. $end
$dumpall
$end
#0
$dumpvars
bx &
0%
1$
0#
0"
bx !
$end
#5
b0 !
b0 &
1"
#10
0"
1%
1#
0$
#15
b1000 !
b1000 &
1"
#20
0"
0%
#25
b100 !
b100 &
1"
#30
0"
#35
b10 !
b10 &
1"
#40
0"
1%
#45
b1001 !
b1001 &
1"
#50
0"
0#
#55
b1100 !
b1100 &
1"
#60
0"
#65
b1110 !
b1110 &
1"
#70
0"
#75
b1111 !
b1111 &
1"
