siso.v
module siso(
    input clk,rst,s_in, 
    output reg s_out
);
reg [3:0] temp;

always @(posedge clk)begin
    if(rst)begin
        s_out <= 0;
        temp <= 4'b0000;
    end

    else begin
        temp <= {s_in,temp[3:1]};
        s_out <= temp[0];
        temp[3] <= s_in;
        
    end

end

endmodule


`timescale 1ps/1ps
module tb;

reg clk,rst,s_in;
wire s_out;

siso dut(
    clk,rst,s_in,s_out
);

initial begin
    {clk,rst,s_in} = 0;
end

always #5 clk = ~clk;
initial begin
    $dumpfile("siso.vcd");
    $dumpvars(0,tb);
    rst =1;
    #10;
    rst =0;
    #5;
    s_in = 1;
    #10;
    s_in= 0;
    #10;
    s_in =0 ; #10;
    s_in =1; #10;
    
    #60;
    $finish;

end
endmodule

siso.vcd
$date
	Fri Aug 14 06:19:10 2026
$end
$version
	Icarus Verilog
$end
$timescale
	1ps
$end
$scope module tb $end
$var wire 1 ! s_out $end
$var reg 1 " clk $end
$var reg 1 # rst $end
$var reg 1 $ s_in $end
$scope module dut $end
$var wire 1 " clk $end
$var wire 1 # rst $end
$var wire 1 $ s_in $end
$var reg 1 ! s_out $end
$var reg 4 % temp [3:0] $end
$upscope $end
$upscope $end
$enddefinitions $end
$comment Show the parameter values. $end
$dumpall
$end
#0
$dumpvars
bx %
0$
1#
0"
x!
$end
#5
b0 %
0!
1"
#10
0"
0#
#15
b1000 %
1"
1$
#20
0"
#25
b100 %
1"
0$
#30
0"
#35
b10 %
1"
#40
0"
#45
b1001 %
1"
1$
#50
0"
#55
1!
b1100 %
1"
#60
0"
#65
0!
b1110 %
1"
#70
0"
#75
b1111 %
1"
#80
0"
#85
1!
1"
