t_latch.v
module t_latch(
    input enb,rst,t,
    output reg q,q_bar
);

    always @(enb) begin
        if(enb)begin
            //reset login 
            if(rst) begin
                q <= 1'b0;
                q_bar <= 1'b1;
            end
            //hold condition 
            else if(t == 1'b0) begin
                q<=q;
                q_bar<=q_bar;
             end

             //toggle condition 
             else if(t == 1'b1)begin
                q<=~q;
                q_bar<=~q_bar;
             end
        end

    end

endmodule


`timescale 1ps/1ps
module t_latch_tb;

reg enb,rst,t;
wire q,q_bar;
t_latch uut(
     enb,rst,t,q,q_bar
);

initial begin
    {enb,rst} =0;
    t = 1;
end
always #5 enb = ~enb;

initial begin
    $dumpfile("t_latch.vcd");
    $dumpvars(0,t_latch_tb);
    
    rst = 1;
    #10;
    rst = 0;
    t = 0;
    #10;
    t = 1;
    #10;
    rst =1;
    #10;

    $finish;
end
endmodule

t_latch.vcd
$date
	Thu Aug 13 20:15:04 2026
$end
$version
	Icarus Verilog
$end
$timescale
	1ps
$end
$scope module t_latch_tb $end
$var wire 1 ! q_bar $end
$var wire 1 " q $end
$var reg 1 # enb $end
$var reg 1 $ rst $end
$var reg 1 % t $end
$scope module uut $end
$var wire 1 # enb $end
$var wire 1 $ rst $end
$var wire 1 % t $end
$var reg 1 " q $end
$var reg 1 ! q_bar $end
$upscope $end
$upscope $end
$enddefinitions $end
$comment Show the parameter values. $end
$dumpall
$end
#0
$dumpvars
1%
1$
0#
x"
x!
$end
#5
1!
0"
1#
#10
0#
0%
0$
#15
1#
#20
0#
1%
#25
0!
1"
1#
#30
0#
1$
#35
1!
0"
1#
#40
0#
