usr.v
module usr(
    input clk,enb,rst,s_in,
    input [3:0]p_in,
    input [1:0]mode,
    output reg s_out,
    output reg [3:0]p_out 
);
reg [3:0]temp;
always@(posedge clk)begin
    if(rst)begin
        temp <= 4'b0000;
        s_out<=1'b0;
        p_out<=4'b0000;
    end
    else begin
        case(mode)
            2'b00: begin //siso operation 
                temp <= {s_in,temp[3:1]};
                s_out <= temp[0];
            end

            2'b01: begin //sipo operation
                p_out <= {s_in, temp[3:1]};
                temp  <= {s_in, temp[3:1]};
            end

            2'b10:begin //piso operation
                 if(enb == 1)begin
                     temp <= p_in;
                 end
                 else if(enb ==0)begin
                     s_out <= temp[0];
                     temp <= temp >> 1'b1;
                 end
            end

            2'b11:begin //pipo operation
                p_out <= p_in;

            end

            default: begin
                p_out<=4'b0000;
                temp <=4'b0000;
                s_out <= 1'b0;
                $monitor("defualt statement has ran ");
            end
        endcase
    end
end

endmodule


`timescale 1ps/1ps
module tb;

reg clk,enb,rst,s_in;
reg [3:0]p_in;
reg [1:0]mode;
wire s_out;
wire [3:0]p_out;

usr dut(clk,enb,rst,s_in,p_in,mode,s_out,p_out);
initial begin
    {clk,enb,rst,s_in,p_in,mode} =0;
end
always #5 clk = ~clk;

initial begin
    $dumpfile("usr.vcd");
    $dumpvars(0,tb);
    rst =1;
    #10;
    rst =0;
   
    #10;
    mode = 2'b00; //siso
    s_in = 1; #10;
    s_in = 0; #10;
    s_in = 0; #10;
    s_in = 1; #10;
    #40;
     enb = 1;

     rst = 1;#10;rst=0;

    mode = 2'b01; //sipo
    s_in = 1; #10;
    s_in = 0; #10;
    s_in = 0; #10;
    s_in = 1; #10;
     enb = 0;
    #40;

    rst = 1;#10;rst=0;

    mode = 2'b10; //piso
    enb=1;
    p_in = 4'b1001;#10;
    enb=0;
    #40;

    rst = 1;#10;rst=0;
    mode = 2'b11; //pipo 
    p_in = 4'b1001;#10;
    #10;
    #200;
    $finish;


end
endmodule

usr.vcd
$date
	Fri Aug 14 08:54:27 2026
$end
$version
	Icarus Verilog
$end
$timescale
	1ps
$end
$scope module tb $end
$var wire 1 ! s_out $end
$var wire 4 " p_out [3:0] $end
$var reg 1 # clk $end
$var reg 1 $ enb $end
$var reg 2 % mode [1:0] $end
$var reg 4 & p_in [3:0] $end
$var reg 1 ' rst $end
$var reg 1 ( s_in $end
$scope module dut $end
$var wire 1 # clk $end
$var wire 1 $ enb $end
$var wire 2 ) mode [1:0] $end
$var wire 4 * p_in [3:0] $end
$var wire 1 ' rst $end
$var wire 1 ( s_in $end
$var reg 4 + p_out [3:0] $end
$var reg 1 ! s_out $end
$var reg 4 , temp [3:0] $end
$upscope $end
$upscope $end
$enddefinitions $end
$comment Show the parameter values. $end
$dumpall
$end
#0
$dumpvars
bx ,
bx +
b0 *
b0 )
0(
1'
b0 &
b0 %
0$
0#
bx "
x!
$end
#5
b0 "
b0 +
0!
b0 ,
1#
#10
0#
0'
#15
1#
#20
0#
1(
#25
b1000 ,
1#
#30
0#
0(
#35
b100 ,
1#
#40
0#
#45
b10 ,
1#
#50
0#
1(
#55
b1001 ,
1#
#60
0#
#65
1!
b1100 ,
1#
#70
0#
#75
0!
b1110 ,
1#
#80
0#
#85
b1111 ,
1#
#90
0#
#95
1!
1#
#100
0#
1'
1$
#105
0!
b0 ,
1#
#110
0#
b1 %
b1 )
0'
#115
b1000 ,
b1000 "
b1000 +
1#
#120
0#
0(
#125
b100 ,
b100 "
b100 +
1#
#130
0#
#135
b10 ,
b10 "
b10 +
1#
#140
0#
1(
#145
b1001 ,
b1001 "
b1001 +
1#
#150
0#
0$
#155
b1100 ,
b1100 "
b1100 +
1#
#160
0#
#165
b1110 ,
b1110 "
b1110 +
1#
#170
0#
#175
b1111 ,
b1111 "
b1111 +
1#
#180
0#
#185
1#
#190
0#
1'
#195
b0 "
b0 +
b0 ,
1#
#200
0#
b1001 &
b1001 *
1$
b10 %
b10 )
0'
#205
b1001 ,
1#
#210
0#
0$
#215
b100 ,
1!
1#
#220
0#
#225
b10 ,
0!
1#
#230
0#
#235
b1 ,
1#
#240
0#
#245
b0 ,
1!
1#
#250
0#
1'
#255
0!
1#
#260
0#
b11 %
b11 )
0'
#265
b1001 "
b1001 +
1#
